gym_togyzkumalak/__init__.py
gym_togyzkumalak/envs/__init__.py
gym_togyzkumalak/envs/togyzkumalak_discrete.py
gym_togyzkumalak/envs/togyzkumalak_env.py
gym_togyzkumalak/togyzkumalak/__init__.py
gym_togyzkumalak/togyzkumalak/board.py
gym_togyzkumalak/togyzkumalak/gamer.py
gym_togyzkumalak/togyzkumalak/kazan.py
gym_togyzkumalak/togyzkumalak/otau.py
gym_togyzkumalak-0.0.2.dist-info/LICENSE
gym_togyzkumalak-0.0.2.dist-info/METADATA
gym_togyzkumalak-0.0.2.dist-info/WHEEL
gym_togyzkumalak-0.0.2.dist-info/top_level.txt
gym_togyzkumalak-0.0.2.dist-info/RECORD
