Metadata-Version: 2.1
Name: gym-togyzkumalak
Version: 0.0.2
Summary: Togyzkumalak is one of the version of mancala games
Home-page: https://github.com/zhasulan/gym-togyzkumalak
Author: Zhassulan Berdibekov
Author-email: zhasulan87@gmail.com
License: UNKNOWN
Platform: UNKNOWN
Requires-Python: >=3.6
Requires-Dist: gym
Requires-Dist: texttable
Requires-Dist: numpy
